meetup/__init__.py
meetup/api.py
meetup/documentation.py
meetup/exceptions.py
meetup/util.py
meetup/api_specification/meetup_v1_services.json
meetup/api_specification/meetup_v2_services.json
meetup/api_specification/meetup_v3_services.json
meetup_api-0.1.1.dist-info/DESCRIPTION.rst
meetup_api-0.1.1.dist-info/METADATA
meetup_api-0.1.1.dist-info/RECORD
meetup_api-0.1.1.dist-info/WHEEL
meetup_api-0.1.1.dist-info/metadata.json
meetup_api-0.1.1.dist-info/top_level.txt
