Metadata-Version: 1.1
Name: meetup-api
Version: 0.1.1
Summary: Python API for Meetup
Home-page: https://github.com/pferate/meetup-api
Author: Pat Ferate
Author-email: UNKNOWN
License: MIT
Keywords: meetup api
Platform: UNKNOWN
Classifier: Development Status :: 3 - Alpha
Classifier: Intended Audience :: Developers
Classifier: License :: OSI Approved :: MIT License
Classifier: Operating System :: OS Independent
Classifier: Programming Language :: Python :: 2
Classifier: Programming Language :: Python :: 2.6
Classifier: Programming Language :: Python :: 2.7
Classifier: Programming Language :: Python :: 3
Classifier: Programming Language :: Python :: 3.4
Classifier: Programming Language :: Python :: 3.5
Classifier: Topic :: Internet :: WWW/HTTP
